pygofile/__init__.py
pygofile/actions.py
pygofile2-1.0.0.dist-info/LICENSE
pygofile2-1.0.0.dist-info/METADATA
pygofile2-1.0.0.dist-info/WHEEL
pygofile2-1.0.0.dist-info/top_level.txt
pygofile2-1.0.0.dist-info/RECORD
