Metadata-Version: 2.1
Name: pygofile2
Version: 1.0.0
Summary: GoFile module API for Python3
Author-email: Micky014 <mickyplay14@gmail.com>
Project-URL: Homepage, https://github.com/Micky014/gofile
Project-URL: Bug Tracker, https://github.com/Micky014/gofile/issues
Classifier: Programming Language :: Python :: 3
Classifier: License :: OSI Approved :: MIT License
Classifier: Operating System :: OS Independent
Requires-Python: >=3.7
License-File: LICENSE
